logsna
