Metadata-Version: 1.1
Name: logsna
Version: 1.1
Summary: A small Python library that provides a sane log output format
Home-page: https://github.com/rspivak/logsna
Author: Ruslan Spivak
Author-email: ruslan.spivak@gmail.com
License: MIT
Platform: UNKNOWN
Classifier: Intended Audience :: Developers
Classifier: License :: OSI Approved :: MIT License
Classifier: Programming Language :: Python
Classifier: Topic :: Software Development :: Libraries
Classifier: Operating System :: Unix
